demonstrable/project/__init__.py
demonstrable/project/cli.py
demonstrable/project/metadata.py
demonstrable/project/process.py
demonstrable/project/resources.py
demonstrable/project/templating.py
demonstrable/project/package_data/__init__.py
demonstrable/project/package_data/new_project/README.md
demonstrable/project/package_data/new_project/pyproject.toml
demonstrable/project/package_data/new_project/uv.lock
demonstrable_project-1.0.4.dist-info/licenses/LICENSE
demonstrable_project-1.0.4.dist-info/METADATA
demonstrable_project-1.0.4.dist-info/WHEEL
demonstrable_project-1.0.4.dist-info/entry_points.txt
demonstrable_project-1.0.4.dist-info/top_level.txt
demonstrable_project-1.0.4.dist-info/RECORD
